py_sysadmin-1.2.9.data/scripts/gen-factory-settings.py
py_sysadmin-1.2.9.data/scripts/migrate.py
py_sysadmin-1.2.9.data/scripts/sysadminctl
py_sysadmin-1.2.9.data/scripts/templater.py
sysadmin/Client.py
sysadmin/ConfigTemplateRenderer.py
sysadmin/LazySysAdmin.py
sysadmin/Migrations.py
sysadmin/SysAdminUser.py
sysadmin/__init__.py
sysadmin/generated/__init__.py
sysadmin/generated/sysadminctl_pb2.py
py_sysadmin-1.2.9.dist-info/LICENSE.txt
py_sysadmin-1.2.9.dist-info/METADATA
py_sysadmin-1.2.9.dist-info/WHEEL
py_sysadmin-1.2.9.dist-info/top_level.txt
py_sysadmin-1.2.9.dist-info/RECORD
