Metadata-Version: 2.1
Name: py-sysadmin
Version: 1.2.9
Summary: Control sysadmin
Home-page: https://github.com/StarryInternet/sysadmin
Author: Starry Inc
Author-email: oss@starry.com
License: UNKNOWN
Platform: UNKNOWN
Classifier: Programming Language :: Python :: 2
Classifier: Programming Language :: Python :: 2.7
Classifier: Programming Language :: Python :: 3.6
Classifier: Programming Language :: Python :: 3.7
Requires-Dist: Jinja2 (<3.0,>=2.8)
Requires-Dist: MarkupSafe (<2.0,>=0.23)
Requires-Dist: protobuf (<4.0,>=3.0)
Requires-Dist: pytz (>=2016.1)
Requires-Dist: PyYAML (<6.0,>=5.1)
Requires-Dist: six (<2.0,>=1.9)
Provides-Extra: test
Requires-Dist: nose (<2.0,>=1.3.0) ; extra == 'test'
